setup.py
anon_requests/__init__.py
anon_requests/base_session.py
anon_requests/exceptions.py
anon_requests/proxy.py
anon_requests/tor.py
anon_requests/utils.py
anon_requests.egg-info/PKG-INFO
anon_requests.egg-info/SOURCES.txt
anon_requests.egg-info/dependency_links.txt
anon_requests.egg-info/requires.txt
anon_requests.egg-info/top_level.txt
anon_requests/proxy_sources/__init__.py
anon_requests/proxy_sources/free_proxy_cz.py
anon_requests/proxy_sources/free_proxy_list.py
anon_requests/proxy_sources/hidemyname.py
anon_requests/proxy_sources/proxydb.py
anon_requests/proxy_sources/proxynova.py
anon_requests/proxy_sources/proxyscan.py
anon_requests/proxy_sources/pubproxy.py
anon_requests/proxy_sources/spysme.py
anon_requests/proxy_sources/spysone.py