Metadata-Version: 1.0
Name: anon-requests
Version: 0.0.1
Summary: anonymous requests
Home-page: https://github.com/OpenJarbas/anon_requests
Author: jarbasAi
Author-email: jarbasai@mailfence.com
License: apache-2.0
Platform: UNKNOWN
